{
  "main": {
    "id": "55c2855ee93080b7",
    "type": "split",
    "children": [
      {
        "id": "268f1dae370b005a",
        "type": "tabs",
        "children": [
          {
            "id": "2faacc5e7fffe78f",
            "type": "leaf",
            "state": {
              "type": "graph",
              "state": {}
            }
          }
        ]
      }
    ],
    "direction": "vertical"
  },
  "left": {
    "id": "75a1d194d5d3911c",
    "type": "split",
    "children": [
      {
        "id": "d036a7712427aff1",
        "type": "tabs",
        "children": [
          {
            "id": "9f2c297e6b3120f9",
            "type": "leaf",
            "state": {
              "type": "file-explorer",
              "state": {
                "sortOrder": "alphabetical"
              }
            }
          },
          {
            "id": "ff88380e43f897da",
            "type": "leaf",
            "state": {
              "type": "search",
              "state": {
                "query": "[[pipelined processor",
                "matchingCase": false,
                "explainSearch": false,
                "collapseAll": false,
                "extraContext": false,
                "sortOrder": "alphabetical"
              }
            }
          },
          {
            "id": "797ea6dfb0fe00cb",
            "type": "leaf",
            "state": {
              "type": "bookmarks",
              "state": {}
            }
          }
        ]
      }
    ],
    "direction": "horizontal",
    "width": 314.5086555480957
  },
  "right": {
    "id": "4b2df34686e9c55e",
    "type": "split",
    "children": [
      {
        "id": "74da6c441cf1fb4a",
        "type": "tabs",
        "children": [
          {
            "id": "2e38b66a332e1c1e",
            "type": "leaf",
            "state": {
              "type": "backlink",
              "state": {
                "collapseAll": false,
                "extraContext": false,
                "sortOrder": "alphabetical",
                "showSearch": false,
                "searchQuery": "",
                "backlinkCollapsed": false,
                "unlinkedCollapsed": true
              }
            }
          },
          {
            "id": "5e1ac50206783911",
            "type": "leaf",
            "state": {
              "type": "outgoing-link",
              "state": {
                "linksCollapsed": false,
                "unlinkedCollapsed": true
              }
            }
          },
          {
            "id": "1c70b918abb9e8ec",
            "type": "leaf",
            "state": {
              "type": "tag",
              "state": {
                "sortOrder": "frequency",
                "useHierarchy": true
              }
            }
          },
          {
            "id": "b26e177017e539ec",
            "type": "leaf",
            "state": {
              "type": "outline",
              "state": {}
            }
          }
        ],
        "currentTab": 1
      }
    ],
    "direction": "horizontal",
    "width": 300,
    "collapsed": true
  },
  "left-ribbon": {
    "hiddenItems": {
      "switcher:Open quick switcher": false,
      "graph:Open graph view": false,
      "canvas:Create new canvas": false,
      "daily-notes:Open today's daily note": false,
      "templates:Insert template": false,
      "command-palette:Open command palette": false,
      "obsidian-excalidraw-plugin:Create new drawing": false
    }
  },
  "active": "2faacc5e7fffe78f",
  "lastOpenFiles": [
    "APPLIED SCIENCE/Engineering and Technology/Electrical Engineering/Computer Engineering/Computer Architecture/Branch Predictors.md",
    "Excalidraw/Drawing 2023-09-05 12.59.45.excalidraw.md",
    "Excalidraw",
    "Excalidraw/Drawing 2023-09-05 12.59.08.excalidraw.md",
    "Untitled.canvas",
    "Untitled",
    "APPLIED SCIENCE/Engineering and Technology/Electrical Engineering/Computer Engineering/Computer Architecture/Instruction Set Architecture.md",
    "APPLIED SCIENCE/Engineering and Technology/Electrical Engineering/Computer Engineering/Computer Architecture/Memory/Branch Target Buffer.md",
    "APPLIED SCIENCE/Engineering and Technology/Electrical Engineering/Computer Engineering/Computer Architecture/Memory/Memory.md",
    "APPLIED SCIENCE/Engineering and Technology/Electrical Engineering/Computer Engineering/Computer Architecture/Memory/Cache Memory.md",
    "APPLIED SCIENCE/Engineering and Technology/Electrical Engineering/Computer Engineering/Computer Architecture/Memory",
    "APPLIED SCIENCE/Engineering and Technology/Electrical Engineering/Computer Engineering/Computer Architecture/Von Neumann Architecture",
    "FORMAL SCIENCE/Computer Science/Theory of Computation/Number Representations/Floating-Point.md",
    "FORMAL SCIENCE/Mathematics/Number Theory/Algebraic Number Theory/Natural Number.md",
    "FORMAL SCIENCE/Mathematics/Number Theory/Algebraic Number Theory/Integer.md",
    "FORMAL SCIENCE/Mathematics/Number Theory/Algebraic Number Theory/Real Number.md",
    "FORMAL SCIENCE/Mathematics/Number Theory/Number Theory.md",
    "FORMAL SCIENCE/Mathematics/Number Theory/Algebraic Number Theory/Algebraic Number Theory.md",
    "Index.md",
    "FORMAL SCIENCE/Mathematics/Number Theory/Algebraic Number Theory",
    "FORMAL SCIENCE/Mathematics/Number Theory",
    "FORMAL SCIENCE/Computer Science/Theory of Computation/Number Representations/Integer (Computer Science).md",
    "APPLIED SCIENCE/Engineering and Technology/Electrical Engineering/Computer Engineering/Computer Architecture/Arithmetic Logic Unit (ALU).md",
    "HUMANITIES/Divinity/Vedic Study/Mahabharata/Bhagavad Gita/Bhagavad Gita.md",
    "HUMANITIES/Divinity/Vedic Study/Mahabharata/Mahabharata.md",
    "HUMANITIES/Divinity/Vedic Study/Vedic Study.md",
    "HUMANITIES/Divinity/Divinity.md",
    "HUMANITIES/Humanities.md",
    "APPLIED SCIENCE/Engineering and Technology/Electrical Engineering/Electrical Engineering.md",
    "APPLIED SCIENCE/Engineering and Technology/Engineering and Technology.md",
    "APPLIED SCIENCE/Engineering and Technology/Electrical Engineering/Computer Engineering/Computer Architecture/Datapath.md",
    "APPLIED SCIENCE/Engineering and Technology/Electrical Engineering/Computer Engineering/Computer Architecture/Iron Law of Performance and Power.md",
    "APPLIED SCIENCE/Engineering and Technology/Electrical Engineering/Computer Engineering/Computer Architecture/Pipelining (Computation).md",
    "FORMAL SCIENCE/Mathematics/Mathematical Logic",
    "FORMAL SCIENCE/Computer Science/Logic (Computer Science)",
    "FORMAL SCIENCE/Computer Science/Theory of Computation/Number Representations",
    "FORMAL SCIENCE/Computer Science/Theory of Computation",
    "NATURAL SCIENCE/Biology/Neuroscience/img/Pearson's diagram of the lobes of the neocortex.png",
    "NATURAL SCIENCE/Biology/Neuroscience/img/Kandel's diagram of the brain.png",
    "APPLIED SCIENCE/Engineering and Technology/Electrical Engineering/Analog Circuits/Linear Circuits/img/Inductor-Capacitor (LC) Tank.png",
    "Untitled 1.canvas",
    "APPLIED SCIENCE/Engineering and Technology/Electrical Engineering/Computer Engineering/Computer Architecture/img/MIPS Five Stage Datapath.png",
    "NATURAL SCIENCE/Biology/Neuroscience/img/Wikipedia's Diagram of the Neuron.png",
    "NATURAL SCIENCE/Biology/Neuroscience/img/Diagram of the Neuron.png",
    "Neuroscience/img/Diagram of the neuron.png"
  ]
}